[
null,
{"id":1,"animationId":0,"description":"","etypeId":1,"traits":[{"code":31,"dataId":1,"value":0},{"code":22,"dataId":0,"value":0}],"iconIndex":0,"name":"\\\\\\ Swords","note":"","params":[0,0,0,0,0,0,0,0],"price":0,"wtypeId":0},
{"id":2,"animationId":295,"description":"A well worn out sword, made for sparring. A personal weapon\npassed down by Gradheart. \\}\\}Combos into \\c[27]Vorporal Strike\\c[0].","etypeId":1,"traits":[{"code":31,"dataId":10,"value":0},{"code":22,"dataId":0,"value":0}],"iconIndex":1479,"name":"Training Sword","note":"<Replace Attack: 242>\n\n<Picture: Sword Rusted>","params":[0,0,5,0,0,0,0,0],"price":50,"wtypeId":2},
{"id":3,"animationId":522,"description":"A sword with a shorter blade than-normal to help\ntrain soldiers. \\}\\}Combos into \\c[27]Vorporal Strike\\c[0].","etypeId":1,"traits":[{"code":31,"dataId":1,"value":0},{"code":22,"dataId":0,"value":0}],"iconIndex":1480,"name":"Short Sword","note":"<Replace Attack: 242>\n\n<Picture: Sword Short>","params":[0,0,8,0,0,0,0,0],"price":100,"wtypeId":2},
{"id":4,"animationId":128,"description":"Copper sword, used in training and in low audience\ntournaments.","etypeId":1,"traits":[{"code":31,"dataId":1,"value":0},{"code":22,"dataId":0,"value":0}],"iconIndex":97,"name":"Copper Sword","note":"","params":[0,0,15,0,0,0,0,0],"price":1000,"wtypeId":2},
{"id":5,"animationId":128,"description":"Bronze sword, used in heavy training and in\nlarge audience tournaments.","etypeId":1,"traits":[{"code":31,"dataId":1,"value":0},{"code":22,"dataId":0,"value":0}],"iconIndex":97,"name":"Bronze Sword","note":"","params":[0,0,20,0,0,0,0,0],"price":2000,"wtypeId":2},
{"id":6,"animationId":128,"description":"Iron sword, used in battles and wars.","etypeId":1,"traits":[{"code":31,"dataId":1,"value":0},{"code":22,"dataId":0,"value":0}],"iconIndex":97,"name":"Iron Sword","note":"","params":[0,0,30,0,0,0,0,0],"price":10000,"wtypeId":2},
{"id":7,"animationId":128,"description":"Mithril sword, made with the rarest materials\nof the world.","etypeId":1,"traits":[{"code":31,"dataId":1,"value":0},{"code":22,"dataId":0,"value":0}],"iconIndex":97,"name":"Mithril Sword","note":"","params":[0,0,40,0,0,0,0,0],"price":20000,"wtypeId":2},
{"id":8,"animationId":128,"description":"Sacred sword that was worn by the mighty ancestral\nwarrior.","etypeId":1,"traits":[{"code":31,"dataId":1,"value":0},{"code":22,"dataId":0,"value":0}],"iconIndex":97,"name":"Draconic Sword","note":"","params":[0,0,45,0,0,0,0,0],"price":25000,"wtypeId":2},
{"id":9,"animationId":0,"description":"","etypeId":1,"traits":[{"code":31,"dataId":1,"value":0},{"code":22,"dataId":0,"value":0}],"iconIndex":0,"name":"","note":"","params":[0,0,0,0,0,0,0,0],"price":0,"wtypeId":0},
{"id":10,"animationId":0,"description":"","etypeId":1,"traits":[{"code":31,"dataId":1,"value":0},{"code":22,"dataId":0,"value":0}],"iconIndex":0,"name":"\\\\\\ Bows","note":"","params":[0,0,0,0,0,0,0,0],"price":0,"wtypeId":0},
{"id":11,"animationId":130,"description":"Small bow to practice.","etypeId":1,"traits":[{"code":31,"dataId":1,"value":0},{"code":22,"dataId":0,"value":0}],"iconIndex":102,"name":"Small Bow","note":"","params":[0,0,5,0,0,0,0,0],"price":100,"wtypeId":7},
{"id":12,"animationId":130,"description":"Longbow to train.","etypeId":1,"traits":[{"code":31,"dataId":1,"value":0},{"code":22,"dataId":0,"value":0}],"iconIndex":102,"name":"Longbow","note":"","params":[0,0,10,0,0,0,0,0],"price":500,"wtypeId":7},
{"id":13,"animationId":130,"description":"Mithril bow, made with the rarest materials\nof the world.","etypeId":1,"traits":[{"code":31,"dataId":1,"value":0},{"code":22,"dataId":0,"value":0}],"iconIndex":102,"name":"Mithril Bow","note":"","params":[0,0,30,0,0,0,0,0],"price":3000,"wtypeId":7},
{"id":14,"animationId":130,"description":"Crossbow used in battles and wars.","etypeId":1,"traits":[{"code":31,"dataId":1,"value":0},{"code":22,"dataId":0,"value":0}],"iconIndex":103,"name":"Crossbow","note":"","params":[0,0,40,0,0,0,10,0],"price":20000,"wtypeId":7},
{"id":15,"animationId":130,"description":"Very fast crossbow.","etypeId":1,"traits":[{"code":31,"dataId":1,"value":0},{"code":22,"dataId":0,"value":0}],"iconIndex":103,"name":"Metal Crossbow","note":"","params":[0,0,50,0,0,0,15,0],"price":50000,"wtypeId":7},
{"id":16,"animationId":0,"description":"","etypeId":1,"traits":[{"code":31,"dataId":1,"value":0},{"code":22,"dataId":0,"value":0}],"iconIndex":0,"name":"","note":"","params":[0,0,0,0,0,0,0,0],"price":0,"wtypeId":0},
{"id":17,"animationId":0,"description":"","etypeId":1,"traits":[{"code":31,"dataId":1,"value":0},{"code":22,"dataId":0,"value":0}],"iconIndex":0,"name":"\\\\\\ Staffs","note":"","params":[0,0,0,0,0,0,0,0],"price":0,"wtypeId":0},
{"id":18,"animationId":123,"description":"Simple wooden staff.","etypeId":1,"traits":[{"code":31,"dataId":1,"value":0},{"code":22,"dataId":0,"value":0}],"iconIndex":101,"name":"Wood Staff","note":"","params":[0,0,2,0,0,0,0,0],"price":10,"wtypeId":6},
{"id":19,"animationId":123,"description":"Magic staff that increases magical powers.","etypeId":1,"traits":[{"code":31,"dataId":1,"value":0},{"code":22,"dataId":0,"value":0}],"iconIndex":101,"name":"Magic Staff","note":"","params":[0,0,3,0,3,0,0,0],"price":50,"wtypeId":6},
{"id":20,"animationId":123,"description":"Staff of rough wood.","etypeId":1,"traits":[{"code":31,"dataId":1,"value":0},{"code":22,"dataId":0,"value":0}],"iconIndex":101,"name":"Strong Wand","note":"","params":[0,0,10,0,0,0,0,0],"price":100,"wtypeId":6},
{"id":21,"animationId":123,"description":"Staff made by a mage.","etypeId":1,"traits":[{"code":31,"dataId":1,"value":0},{"code":22,"dataId":0,"value":0}],"iconIndex":101,"name":"Mage Staff","note":"","params":[0,0,10,0,8,3,0,0],"price":500,"wtypeId":6},
{"id":22,"animationId":123,"description":"Sacred staff touched by an angel.","etypeId":1,"traits":[{"code":31,"dataId":1,"value":0},{"code":22,"dataId":0,"value":0}],"iconIndex":101,"name":"Sacred Staff","note":"","params":[0,0,20,0,15,10,0,0],"price":3000,"wtypeId":6},
{"id":23,"animationId":0,"description":"","etypeId":1,"traits":[{"code":31,"dataId":1,"value":0},{"code":22,"dataId":0,"value":0}],"iconIndex":0,"name":"","note":"","params":[0,0,0,0,0,0,0,0],"price":0,"wtypeId":0},
{"id":24,"animationId":0,"description":"","etypeId":1,"traits":[{"code":31,"dataId":1,"value":0},{"code":22,"dataId":0,"value":0}],"iconIndex":0,"name":"\\\\\\ Axes","note":"","params":[0,0,0,0,0,0,0,0],"price":0,"wtypeId":0},
{"id":25,"animationId":299,"description":"Small axe for training.","etypeId":1,"traits":[{"code":31,"dataId":1,"value":0},{"code":22,"dataId":0,"value":0}],"iconIndex":99,"name":"Small Axe","note":"","params":[0,0,6,0,0,0,0,0],"price":75,"wtypeId":4},
{"id":26,"animationId":299,"description":"Big axe to defend yourself.","etypeId":1,"traits":[{"code":31,"dataId":11,"value":0},{"code":22,"dataId":0,"value":0}],"iconIndex":99,"name":"Big Axe","note":"<Replace Attack: 290>","params":[0,0,12,0,0,0,0,0],"price":150,"wtypeId":4},
{"id":27,"animationId":129,"description":"Sharp and heavy axe.","etypeId":1,"traits":[{"code":31,"dataId":1,"value":0},{"code":22,"dataId":0,"value":0}],"iconIndex":99,"name":"Woodcutter Axe","note":"","params":[0,0,20,0,0,0,-5,0],"price":500,"wtypeId":4},
{"id":28,"animationId":128,"description":"War axe, used in battles and wars.","etypeId":1,"traits":[{"code":31,"dataId":1,"value":0},{"code":22,"dataId":0,"value":0}],"iconIndex":99,"name":"War Axe","note":"","params":[0,0,25,0,0,0,-5,0],"price":2000,"wtypeId":4},
{"id":29,"animationId":128,"description":"Mithril axe, made with the rarest materials\nof the world.","etypeId":1,"traits":[{"code":31,"dataId":1,"value":0},{"code":22,"dataId":0,"value":0}],"iconIndex":99,"name":"Mithril Axe","note":"","params":[0,0,35,0,0,0,-5,0],"price":10000,"wtypeId":4},
{"id":30,"animationId":0,"description":"","etypeId":1,"traits":[{"code":31,"dataId":1,"value":0},{"code":22,"dataId":0,"value":0}],"iconIndex":0,"name":"","note":"","params":[0,0,0,0,0,0,0,0],"price":0,"wtypeId":0},
{"id":31,"animationId":0,"description":"","etypeId":1,"traits":[{"code":31,"dataId":1,"value":0},{"code":22,"dataId":0,"value":0}],"iconIndex":0,"name":"\\\\\\ Claws","note":"","params":[0,0,0,0,0,0,0,0],"price":0,"wtypeId":0},
{"id":32,"animationId":135,"description":"A training claw.","etypeId":1,"traits":[{"code":31,"dataId":1,"value":0},{"code":22,"dataId":0,"value":0}],"iconIndex":105,"name":"Training Claw","note":"","params":[0,0,10,0,0,0,-1,0],"price":100,"wtypeId":10},
{"id":33,"animationId":135,"description":"A bronze claw, can be used with quickness.","etypeId":1,"traits":[{"code":31,"dataId":1,"value":0},{"code":22,"dataId":0,"value":0}],"iconIndex":105,"name":"Bronze Claw","note":"","params":[0,0,15,0,0,0,5,0],"price":525,"wtypeId":10},
{"id":34,"animationId":135,"description":"A training claw, it is very sharp.","etypeId":1,"traits":[{"code":31,"dataId":1,"value":0},{"code":22,"dataId":0,"value":0}],"iconIndex":105,"name":"Iron Claw","note":"","params":[0,0,20,0,0,0,5,0],"price":975,"wtypeId":10},
{"id":35,"animationId":135,"description":"A mithril claw. Very strong, very light and rare.","etypeId":1,"traits":[{"code":31,"dataId":1,"value":0},{"code":22,"dataId":0,"value":0}],"iconIndex":105,"name":"Mithril Claw","note":"","params":[0,0,30,0,0,0,10,0],"price":4998,"wtypeId":10},
{"id":36,"animationId":0,"description":"","etypeId":1,"traits":[{"code":31,"dataId":1,"value":0},{"code":22,"dataId":0,"value":0}],"iconIndex":0,"name":"","note":"","params":[0,0,0,0,0,0,0,0],"price":0,"wtypeId":0},
{"id":37,"animationId":0,"description":"","etypeId":1,"traits":[{"code":31,"dataId":1,"value":0},{"code":22,"dataId":0,"value":0}],"iconIndex":0,"name":"\\\\\\ Fire Guns","note":"","params":[0,0,0,0,0,0,0,0],"price":0,"wtypeId":0},
{"id":38,"animationId":111,"description":"A light pistol. Look where you're going to shoot.","etypeId":1,"traits":[{"code":31,"dataId":1,"value":0},{"code":22,"dataId":0,"value":0}],"iconIndex":115,"name":"Pistol","note":"","params":[0,0,15,0,0,0,5,0],"price":1000,"wtypeId":9},
{"id":39,"animationId":111,"description":"A police taser. Leave enemies stunned by\nshoot.","etypeId":1,"traits":[{"code":31,"dataId":1,"value":0},{"code":22,"dataId":0,"value":0},{"code":32,"dataId":13,"value":0.8}],"iconIndex":115,"name":"Taser","note":"","params":[0,0,20,0,0,0,0,0],"price":1500,"wtypeId":9},
{"id":40,"animationId":112,"description":"It's heavy, but you can hit multiple shots.","etypeId":1,"traits":[{"code":31,"dataId":1,"value":0},{"code":22,"dataId":0,"value":0},{"code":34,"dataId":0,"value":2}],"iconIndex":116,"name":"Machine Gun","note":"","params":[0,0,15,0,0,0,-1,0],"price":5000,"wtypeId":9},
{"id":41,"animationId":0,"description":"","etypeId":1,"traits":[{"code":31,"dataId":1,"value":0},{"code":22,"dataId":0,"value":0}],"iconIndex":0,"name":"","note":"","params":[0,0,0,0,0,0,0,0],"price":0,"wtypeId":0},
{"id":42,"animationId":0,"description":"","etypeId":1,"traits":[{"code":31,"dataId":1,"value":0},{"code":22,"dataId":0,"value":0}],"iconIndex":0,"name":"","note":"","params":[0,0,0,0,0,0,0,0],"price":0,"wtypeId":0},
{"id":43,"animationId":0,"description":"","etypeId":1,"traits":[{"code":31,"dataId":1,"value":0},{"code":22,"dataId":0,"value":0}],"iconIndex":0,"name":"","note":"","params":[0,0,0,0,0,0,0,0],"price":0,"wtypeId":0},
{"id":44,"animationId":0,"description":"","etypeId":1,"traits":[{"code":31,"dataId":1,"value":0},{"code":22,"dataId":0,"value":0}],"iconIndex":0,"name":"\\\\\\ Rapiers","note":"","params":[0,0,0,0,0,0,0,0],"price":0,"wtypeId":0},
{"id":45,"animationId":193,"description":"A sword used to practice fencing.","etypeId":1,"traits":[{"code":31,"dataId":13,"value":0},{"code":22,"dataId":0,"value":0}],"iconIndex":1267,"name":"Rapier","note":"<Replace Attack: Rapier Attack>","params":[0,0,8,0,0,0,0,0],"price":500,"wtypeId":23},
{"id":46,"animationId":0,"description":"","etypeId":1,"traits":[{"code":31,"dataId":1,"value":0},{"code":22,"dataId":0,"value":0}],"iconIndex":0,"name":"","note":"","params":[0,0,0,0,0,0,0,0],"price":0,"wtypeId":0},
{"id":47,"animationId":0,"description":"","etypeId":1,"traits":[{"code":31,"dataId":1,"value":0},{"code":22,"dataId":0,"value":0}],"iconIndex":0,"name":"","note":"","params":[0,0,0,0,0,0,0,0],"price":0,"wtypeId":0},
{"id":48,"animationId":0,"description":"","etypeId":1,"traits":[{"code":31,"dataId":1,"value":0},{"code":22,"dataId":0,"value":0}],"iconIndex":0,"name":"","note":"","params":[0,0,0,0,0,0,0,0],"price":0,"wtypeId":0},
{"id":49,"animationId":0,"description":"","etypeId":1,"traits":[{"code":31,"dataId":1,"value":0},{"code":22,"dataId":0,"value":0}],"iconIndex":0,"name":"","note":"","params":[0,0,0,0,0,0,0,0],"price":0,"wtypeId":0},
{"id":50,"animationId":0,"description":"","etypeId":1,"traits":[{"code":31,"dataId":1,"value":0},{"code":22,"dataId":0,"value":0}],"iconIndex":0,"name":"","note":"","params":[0,0,0,0,0,0,0,0],"price":0,"wtypeId":0},
{"id":51,"animationId":0,"description":"","etypeId":1,"traits":[{"code":31,"dataId":1,"value":0},{"code":22,"dataId":0,"value":0}],"iconIndex":0,"name":"\\\\\\ Spears","note":"","params":[0,0,0,0,0,0,0,0],"price":0,"wtypeId":0},
{"id":52,"animationId":192,"description":"A short spear specialized in thrusting. ","etypeId":1,"traits":[{"code":31,"dataId":1,"value":0},{"code":22,"dataId":0,"value":0}],"iconIndex":107,"name":"Short Spear","note":"","params":[0,0,6,0,0,0,0,0],"price":320,"wtypeId":12},
{"id":53,"animationId":192,"description":"A spear with the longest handle possible. ","etypeId":1,"traits":[{"code":31,"dataId":1,"value":0},{"code":22,"dataId":0,"value":0}],"iconIndex":107,"name":"Long Spear","note":"","params":[0,0,12,0,0,0,0,0],"price":890,"wtypeId":12},
{"id":54,"animationId":192,"description":"A spear with an axe-head at its tip.","etypeId":1,"traits":[{"code":31,"dataId":1,"value":0},{"code":22,"dataId":0,"value":0}],"iconIndex":107,"name":"Halberd","note":"","params":[0,0,18,0,0,0,0,0],"price":1760,"wtypeId":12},
{"id":55,"animationId":192,"description":"A spear forged of mithril.","etypeId":1,"traits":[{"code":31,"dataId":1,"value":0},{"code":22,"dataId":0,"value":0}],"iconIndex":107,"name":"Mithril Spear","note":"","params":[0,0,24,0,0,0,0,0],"price":3420,"wtypeId":12},
{"id":56,"animationId":192,"description":"A spear forged of dragon’s fangs.","etypeId":1,"traits":[{"code":31,"dataId":1,"value":0},{"code":22,"dataId":0,"value":0}],"iconIndex":107,"name":"Dragon Spear","note":"","params":[0,0,32,0,0,0,0,0],"price":5980,"wtypeId":12},
{"id":57,"animationId":0,"description":"","etypeId":1,"traits":[{"code":31,"dataId":1,"value":0},{"code":22,"dataId":0,"value":0}],"iconIndex":0,"name":"","note":"","params":[0,0,0,0,0,0,0,0],"price":0,"wtypeId":0},
{"id":58,"animationId":0,"description":"","etypeId":1,"traits":[{"code":31,"dataId":1,"value":0},{"code":22,"dataId":0,"value":0}],"iconIndex":0,"name":"","note":"","params":[0,0,0,0,0,0,0,0],"price":0,"wtypeId":0},
{"id":59,"animationId":0,"description":"","etypeId":1,"traits":[{"code":31,"dataId":1,"value":0},{"code":22,"dataId":0,"value":0}],"iconIndex":0,"name":"","note":"","params":[0,0,0,0,0,0,0,0],"price":0,"wtypeId":0},
{"id":60,"animationId":0,"description":"","etypeId":1,"traits":[{"code":31,"dataId":1,"value":0},{"code":22,"dataId":0,"value":0}],"iconIndex":0,"name":"\\\\\\ Daggers","note":"","params":[0,0,0,0,0,0,0,0],"price":0,"wtypeId":0},
{"id":61,"animationId":130,"description":"A training dagger.","etypeId":1,"traits":[{"code":31,"dataId":1,"value":0},{"code":22,"dataId":0,"value":0}],"iconIndex":1408,"name":"Training Dagger","note":"","params":[0,0,10,0,0,0,-1,0],"price":100,"wtypeId":1},
{"id":62,"animationId":130,"description":"A bronze dagger, can be used with quickness.","etypeId":1,"traits":[{"code":31,"dataId":1,"value":0},{"code":22,"dataId":0,"value":0}],"iconIndex":1408,"name":"Bronze Dagger","note":"","params":[0,0,15,0,0,0,5,0],"price":525,"wtypeId":1},
{"id":63,"animationId":130,"description":"A training dagger, it is very sharp.","etypeId":1,"traits":[{"code":31,"dataId":1,"value":0},{"code":22,"dataId":0,"value":0}],"iconIndex":1408,"name":"Iron Dagger","note":"","params":[0,0,20,0,0,0,5,0],"price":975,"wtypeId":1},
{"id":64,"animationId":130,"description":"A mithril dagger. Very strong, very light and rare.","etypeId":1,"traits":[{"code":31,"dataId":1,"value":0},{"code":22,"dataId":0,"value":0}],"iconIndex":1408,"name":"Mithril Dagger","note":"","params":[0,0,30,0,0,0,10,0],"price":5000,"wtypeId":1},
{"id":65,"animationId":130,"description":"Sacred dagger that was worn by the mighty ancestral\nassassin.","etypeId":1,"traits":[{"code":31,"dataId":1,"value":0},{"code":22,"dataId":0,"value":0}],"iconIndex":1552,"name":"Draconic Dagger","note":"","params":[0,0,40,0,0,0,0,0],"price":10000,"wtypeId":1},
{"id":66,"animationId":0,"description":"","etypeId":1,"traits":[{"code":31,"dataId":1,"value":0},{"code":22,"dataId":0,"value":0}],"iconIndex":0,"name":"","note":"","params":[0,0,0,0,0,0,0,0],"price":0,"wtypeId":0},
{"id":67,"animationId":0,"description":"","etypeId":1,"traits":[{"code":31,"dataId":1,"value":0},{"code":22,"dataId":0,"value":0}],"iconIndex":0,"name":"","note":"","params":[0,0,0,0,0,0,0,0],"price":0,"wtypeId":0},
{"id":68,"animationId":0,"description":"","etypeId":1,"traits":[{"code":31,"dataId":1,"value":0},{"code":22,"dataId":0,"value":0}],"iconIndex":0,"name":"","note":"","params":[0,0,0,0,0,0,0,0],"price":0,"wtypeId":0},
{"id":69,"animationId":0,"description":"","etypeId":1,"traits":[{"code":31,"dataId":1,"value":0},{"code":22,"dataId":0,"value":0}],"iconIndex":0,"name":"\\\\\\ Bags","note":"","params":[0,0,0,0,0,0,0,0],"price":0,"wtypeId":0},
{"id":70,"animationId":244,"description":"A simple bag of magical tricks.","etypeId":1,"traits":[{"code":31,"dataId":15,"value":0},{"code":22,"dataId":0,"value":0}],"iconIndex":208,"name":"Bag of Tricks","note":"<Replace Attack: Trick Attack>\n<Picture: Magic Bag>","params":[0,0,0,0,5,0,0,0],"price":0,"wtypeId":17},
{"id":71,"animationId":0,"description":"","etypeId":1,"traits":[{"code":31,"dataId":1,"value":0},{"code":22,"dataId":0,"value":0}],"iconIndex":0,"name":"","note":"","params":[0,0,0,0,0,0,0,0],"price":0,"wtypeId":0},
{"id":72,"animationId":0,"description":"","etypeId":1,"traits":[{"code":31,"dataId":1,"value":0},{"code":22,"dataId":0,"value":0}],"iconIndex":0,"name":"","note":"","params":[0,0,0,0,0,0,0,0],"price":0,"wtypeId":0},
{"id":73,"animationId":0,"description":"","etypeId":1,"traits":[{"code":31,"dataId":1,"value":0},{"code":22,"dataId":0,"value":0}],"iconIndex":0,"name":"","note":"","params":[0,0,0,0,0,0,0,0],"price":0,"wtypeId":0},
{"id":74,"animationId":0,"description":"","etypeId":1,"traits":[{"code":31,"dataId":1,"value":0},{"code":22,"dataId":0,"value":0}],"iconIndex":0,"name":"","note":"","params":[0,0,0,0,0,0,0,0],"price":0,"wtypeId":0},
{"id":75,"animationId":0,"description":"","etypeId":1,"traits":[{"code":31,"dataId":1,"value":0},{"code":22,"dataId":0,"value":0}],"iconIndex":0,"name":"","note":"","params":[0,0,0,0,0,0,0,0],"price":0,"wtypeId":0},
{"id":76,"animationId":0,"description":"","etypeId":1,"traits":[{"code":31,"dataId":1,"value":0},{"code":22,"dataId":0,"value":0}],"iconIndex":0,"name":"","note":"","params":[0,0,0,0,0,0,0,0],"price":0,"wtypeId":0},
{"id":77,"animationId":0,"description":"","etypeId":1,"traits":[{"code":31,"dataId":1,"value":0},{"code":22,"dataId":0,"value":0}],"iconIndex":0,"name":"","note":"","params":[0,0,0,0,0,0,0,0],"price":0,"wtypeId":0},
{"id":78,"animationId":0,"description":"","etypeId":1,"traits":[{"code":31,"dataId":1,"value":0},{"code":22,"dataId":0,"value":0}],"iconIndex":0,"name":"","note":"","params":[0,0,0,0,0,0,0,0],"price":0,"wtypeId":0},
{"id":79,"animationId":0,"description":"","etypeId":1,"traits":[{"code":31,"dataId":1,"value":0},{"code":22,"dataId":0,"value":0}],"iconIndex":0,"name":"","note":"","params":[0,0,0,0,0,0,0,0],"price":0,"wtypeId":0},
{"id":80,"animationId":0,"description":"","etypeId":1,"traits":[{"code":31,"dataId":1,"value":0},{"code":22,"dataId":0,"value":0}],"iconIndex":0,"name":"","note":"","params":[0,0,0,0,0,0,0,0],"price":0,"wtypeId":0},
{"id":81,"animationId":0,"description":"","etypeId":1,"traits":[{"code":31,"dataId":1,"value":0},{"code":22,"dataId":0,"value":0}],"iconIndex":0,"name":"","note":"","params":[0,0,0,0,0,0,0,0],"price":0,"wtypeId":0},
{"id":82,"animationId":0,"description":"","etypeId":1,"traits":[{"code":31,"dataId":1,"value":0},{"code":22,"dataId":0,"value":0}],"iconIndex":0,"name":"","note":"","params":[0,0,0,0,0,0,0,0],"price":0,"wtypeId":0}
]